{"type":"View","props":{"width":621,"height":146},"compId":2,"child":[{"type":"Image","props":{"y":0,"width":621,"skin":"res/image/com/common/image_itemBg.png","sizeGrid":"20,20,20,20","height":146},"compId":23},{"type":"Image","props":{"y":92,"x":13,"width":596,"skin":"res/image/com/common/image_line2_1.png","sizeGrid":"0,20,0,20"},"compId":71},{"type":"Image","props":{"y":19.5,"x":19.5,"var":"imgBg1","skin":"res/image/com/jingji/imgnull.png","scaleY":0.9,"scaleX":0.9},"compId":59},{"type":"Image","props":{"y":19.5,"x":88.5,"var":"imgBg2","skin":"res/image/com/jingji/imgnull.png","scaleY":0.9,"scaleX":0.9},"compId":60},{"type":"Image","props":{"y":19.5,"x":158,"var":"imgBg3","skin":"res/image/com/jingji/imgnull.png","scaleY":0.9,"scaleX":0.9},"compId":61},{"type":"Image","props":{"y":103,"x":493.5,"width":98,"skin":"res/image/com/common/img_shuzidi.png","height":30},"compId":67},{"type":"Text","props":{"y":108,"x":506,"width":73,"var":"txtNeedZDL","valign":"middle","text":"9999","fontSize":22,"color":"#9d600f","align":"center","runtime":"Laya.Text"},"compId":31,"child":[{"type":"Script","props":{"customType":"2","runtime":"utils/script/TTFComponent.ts"},"compId":66}]},{"type":"Text","props":{"y":107,"x":19.5,"width":124,"var":"txtName","text":"队伍名字","fontSize":22,"font":"Arial","color":"#6a5853","bold":true,"runtime":"Laya.Text"},"compId":36},{"type":"Head","props":{"y":19,"x":19.5,"var":"head1","scaleY":0.6,"scaleX":0.6,"runtime":"module/grid/Head.ts"},"compId":40},{"type":"Head","props":{"y":19,"x":89.5,"var":"head2","scaleY":0.6,"scaleX":0.6,"runtime":"module/grid/Head.ts"},"compId":41},{"type":"Head","props":{"y":19,"x":159,"var":"head3","scaleY":0.6,"scaleX":0.6,"runtime":"module/grid/Head.ts"},"compId":42},{"type":"Button","props":{"y":19.5,"x":442,"var":"btnApply","stateNum":1,"skin":"res/image/com/common/btn_yellow.png"},"compId":46,"child":[{"type":"Script","props":{"runtime":"utils/script/ScaleButton.ts"},"compId":47},{"type":"Text","props":{"y":11,"x":51,"text":"申请","strokeColor":"#ac5d17","stroke":2,"fontSize":32,"color":"#f9f7df","runtime":"Laya.Text"},"compId":68,"child":[{"type":"Script","props":{"customType":"1","runtime":"utils/script/TTFComponent.ts"},"compId":69}]}]},{"type":"Label","props":{"y":107,"x":372,"text":"战力要求：","fontSize":24,"color":"#d45647"},"compId":54,"child":[{"type":"Script","props":{"customType":"2","runtime":"utils/script/TTFComponent.ts"},"compId":65}]},{"type":"Image","props":{"y":20.5,"x":235,"width":200,"skin":"res/image/com/common/bg_zhangliB.png","sizeGrid":"0,68,0,74"},"compId":55},{"type":"Text","props":{"y":39,"x":291,"width":100,"var":"txtZdl","value":"12345678","text":"999","strokeColor":"#8a4339","stroke":1,"fontSize":24,"color":"#fdfce1","align":"left","runtime":"Laya.Text"},"compId":56,"child":[{"type":"Script","props":{"customType":"2","runtime":"utils/script/TTFComponent.ts"},"compId":70}]},{"type":"Image","props":{"y":102,"x":162,"skin":"res/image/com/common/img_qyd.png"},"compId":57},{"type":"Text","props":{"y":108,"x":159,"width":55,"var":"txtSvrName","text":"S55","strokeColor":"#b24438","stroke":1,"fontSize":20,"color":"#fefaef","align":"center","runtime":"Laya.Text"},"compId":58}],"loadList":["res/image/com/common/image_itemBg.png","res/image/com/common/image_line2_1.png","res/image/com/jingji/imgnull.png","res/image/com/common/img_shuzidi.png","res/image/com/config/grid/Head.scene","res/image/com/common/btn_yellow.png","res/image/com/common/bg_zhangliB.png","res/image/com/common/img_qyd.png"],"loadList3D":[]}