{"type":"View","props":{"y":0,"width":720,"top":0,"height":1280,"bottom":0},"compId":2,"child":[{"type":"Image","props":{"top":1057,"skin":"res/image/com/common/bg_xiaui.png","centerX":0,"bottom":0,"sizeGrid":"21,0,167,0"},"compId":64},{"type":"Box","props":{"width":720,"var":"imgBg","top":96,"styleSkin":"res/image/cn/welfare/bg_mrqd.png","centerX":0},"compId":14,"child":[{"type":"Sprite","props":{"texture":"res/image/cn/welfare/bg_mrqd.png"},"compId":49,"child":[{"type":"Script","props":{"runtime":"utils/script/LoadResImage.ts"},"compId":63}]},{"type":"Label","props":{"y":236,"x":383,"width":178,"var":"txtDay","text":"20","strokeColor":"#a93c17","stroke":2,"height":80,"fontSize":80,"color":"#f7f4d9","align":"right"},"compId":29,"child":[{"type":"Script","props":{"customType":"1","runtime":"utils/script/TTFComponent.ts"},"compId":51}]},{"type":"Label","props":{"y":199,"x":425,"width":43,"var":"txtMonth","text":"9","height":34,"fontSize":34,"color":"#f9d982","align":"center"},"compId":30,"child":[{"type":"Script","props":{"customType":"1","runtime":"utils/script/TTFComponent.ts"},"compId":54}]},{"type":"Text","props":{"y":315,"x":484,"var":"txtSould","text":"召唤武将","strokeColor":"#fffbef","stroke":3,"fontSize":24,"color":"#22925f","runtime":"Laya.Text"},"compId":61,"child":[{"type":"Script","props":{"customType":"1","runtime":"utils/script/TTFComponent.ts"},"compId":62}]},{"type":"List","props":{"y":389,"width":550,"var":"list","spaceY":8,"spaceX":8,"repeatX":5,"height":480,"centerX":3},"compId":25,"child":[{"type":"DaliSignItem","props":{"runtime":"module/dailySign/DailySignItem.ts","renderType":"render"},"compId":28}]},{"type":"Button","props":{"y":196,"x":79,"var":"btnRule","skin":"res/image/com/common/btn_wenhao.png","stateNum":1,"label":" "},"compId":26,"child":[{"type":"Script","props":{"runtime":"utils/script/ScaleButton.ts"},"compId":27}]},{"type":"Button","props":{"y":909,"x":237,"var":"btnSign","stateNum":1,"skin":"res/image/com/common/btn_yellow1.png"},"compId":21,"child":[{"type":"Script","props":{"runtime":"utils/script/ScaleButton.ts"},"compId":22},{"type":"Label","props":{"y":0,"x":0,"var":"fontSign","text":"签到","strokeColor":"#fff47e","stroke":3,"fontSize":36,"color":"#704534","centerY":-2,"centerX":0},"compId":45,"child":[{"type":"Script","props":{"customType":"1","runtime":"utils/script/TTFComponent.ts"},"compId":50}]}]},{"type":"Box","props":{"y":201,"x":477,"var":"boxDesc"},"compId":65,"child":[{"type":"Label","props":{"y":70,"x":88,"var":"txtDesc4","text":"日","strokeColor":"#a93c17","stroke":2,"fontSize":36,"color":"#f7f4d9"},"compId":52,"child":[{"type":"Script","props":{"customType":"1","runtime":"utils/script/TTFComponent.ts"},"compId":53}]},{"type":"Label","props":{"var":"txtDesc1","text":"月","fontSize":32,"color":"#f9d982","align":"center"},"compId":59,"child":[{"type":"Script","props":{"customType":"1","runtime":"utils/script/TTFComponent.ts"},"compId":60}]},{"type":"Label","props":{"x":45,"var":"txtDesc2","text":"签","fontSize":32,"color":"#f9d982","align":"center"},"compId":57,"child":[{"type":"Script","props":{"customType":"1","runtime":"utils/script/TTFComponent.ts"},"compId":58}]},{"type":"Label","props":{"x":89,"var":"txtDesc3","text":"到","fontSize":32,"color":"#f9d982","align":"center"},"compId":55,"child":[{"type":"Script","props":{"customType":"1","runtime":"utils/script/TTFComponent.ts"},"compId":56}]}]}]}],"loadList":["res/image/com/common/bg_xiaui.png","res/image/cn/welfare/bg_mrqd.png","res/image/com/config/dailySign/DaliSignItem.scene","res/image/com/common/btn_wenhao.png","res/image/com/common/btn_yellow1.png"],"loadList3D":[]}