{"type":"View","props":{"width":720,"height":1280},"compId":2,"child":[{"type":"Box","props":{"width":691,"height":952,"centerY":0,"centerX":0},"compId":27,"child":[{"type":"Image","props":{"y":0,"x":0,"width":691,"skin":"res/image/com/common/bg_alert.png","sizeGrid":"190,0,345,0","height":952},"compId":37},{"type":"Image","props":{"y":60,"x":457,"skin":"res/image/com/common/img_titlezhuangshi.png","scaleX":-1},"compId":48},{"type":"Image","props":{"y":60,"x":230,"width":28,"skin":"res/image/com/common/img_titlezhuangshi.png","height":15},"compId":49},{"type":"Image","props":{"y":112,"x":41,"skin":"res/image/com/common/image_zhuangshi.png"},"compId":52},{"type":"Label","props":{"y":52,"width":326,"text":"运输列表","name":"txtTitle","height":34,"fontSize":34,"color":"#81523a","centerX":0,"align":"center"},"compId":50,"child":[{"type":"Script","props":{"customType":"1","runtime":"utils/script/TTFComponent.ts"},"compId":51}]},{"type":"Image","props":{"y":105,"x":507,"width":146,"skin":"res/image/com/common/frame_jinbidi.png","height":34,"sizeGrid":"16,20,13,24"},"compId":42,"child":[{"type":"Image","props":{"y":5,"x":-2,"skin":"res/image/com/common/icon_zuanshi.png"},"compId":18},{"type":"Text","props":{"y":6,"x":26,"width":111,"var":"txtCnt","text":"5678","strokeColor":"#fdfbe7","stroke":2,"height":24,"fontSize":24,"color":"#754333","align":"center","runtime":"Laya.Text"},"compId":19,"child":[{"type":"Script","props":{"y":0,"x":0,"customType":"2","runtime":"utils/script/TTFComponent.ts"},"compId":57}]}]},{"type":"Button","props":{"width":62,"var":"btnClose","stateNum":1,"skin":"res/image/com/common/btn_close2.png","right":-9,"height":65,"centerY":-458},"compId":20},{"type":"Box","props":{"y":291,"width":621,"visible":false,"name":"itemParent","height":137,"centerX":0},"compId":58,"child":[{"type":"Box","props":{"y":0,"x":0,"width":621,"name":"ItemBg","height":137},"compId":59,"child":[{"type":"Script","props":{"y":0,"x":0,"runtime":"utils/rapidScroll/RapidItem.ts"},"compId":60},{"type":"Image","props":{"y":0,"x":0,"width":621,"skin":"res/image/com/common/image_itemBg.png","sizeGrid":"37,37,37,37","name":"imgBg","height":137},"compId":61}]},{"type":"Box","props":{"y":0,"x":0,"width":621,"sizeGrid":"0,62,0,57","name":"ItemImage","mouseThrough":true,"height":137},"compId":77,"child":[{"type":"Script","props":{"runtime":"utils/rapidScroll/RapidItem.ts"},"compId":78},{"type":"Image","props":{"y":24,"x":464,"width":21,"skin":"res/image/com/ship/zd_icon_shijian.png","height":20},"compId":81},{"type":"Image","props":{"y":12.5,"x":49,"skin":"res/image/com/ship/frame_ship1.png","name":"imgShip"},"compId":82},{"type":"Image","props":{"y":1,"x":9,"skin":"res/image/com/ship/cy_jiaobiao_1.png","name":"imgShipName"},"compId":83}]},{"type":"Box","props":{"y":0,"x":0,"width":621,"sizeGrid":"0,62,0,57","name":"ItemBtn","mouseThrough":true,"height":137},"compId":86,"child":[{"type":"Script","props":{"runtime":"utils/rapidScroll/RapidItem.ts"},"compId":87},{"type":"Button","props":{"y":53,"x":441,"stateNum":1,"skin":"res/image/com/common/btn_yellow.png","name":"btnSport"},"compId":92,"child":[{"type":"Image","props":{"y":17,"x":13,"skin":"res/image/com/common/icon_zuanshi.png"},"compId":93},{"type":"Text","props":{"y":26,"x":38,"width":64,"text":"5678","strokeColor":"#ac5d17","stroke":3,"name":"txtCnt","height":24,"fontSize":24,"color":"#f9f7df","runtime":"Laya.Text"},"compId":94,"child":[{"type":"Script","props":{"customType":"1","runtime":"utils/script/TTFComponent.ts"},"compId":97}]},{"type":"Text","props":{"y":15,"x":88.5,"width":56,"text":"押运","strokeColor":"#ac5d17","stroke":3,"height":28,"fontSize":28,"color":"#f9f7df","runtime":"Laya.Text"},"compId":95,"child":[{"type":"Script","props":{"y":0,"x":0,"customType":"1","runtime":"utils/script/TTFComponent.ts"},"compId":98}]},{"type":"Script","props":{"runtime":"utils/script/ScaleButton.ts"},"compId":96}]}]},{"type":"Box","props":{"y":0,"x":182,"width":256,"sizeGrid":"0,62,0,57","name":"GridBg","hitTestPrior":false,"height":137},"compId":63,"child":[{"type":"Script","props":{"runtime":"utils/rapidScroll/RapidItem.ts"},"compId":64}]},{"type":"Box","props":{"y":0,"x":182,"width":256,"sizeGrid":"0,62,0,57","name":"GridIcon","height":137},"compId":65,"child":[{"type":"Script","props":{"runtime":"utils/rapidScroll/RapidItem.ts"},"compId":66}]},{"type":"Box","props":{"y":0,"x":182,"width":256,"sizeGrid":"0,62,0,57","name":"GridAnim","height":137},"compId":67,"child":[{"type":"Script","props":{"runtime":"utils/rapidScroll/RapidItem.ts"},"compId":68}]},{"type":"Box","props":{"y":0,"x":182,"width":256,"sizeGrid":"0,62,0,57","name":"GridInfo","height":137},"compId":69,"child":[{"type":"Script","props":{"runtime":"utils/rapidScroll/RapidItem.ts"},"compId":70}]},{"type":"Box","props":{"y":0,"x":182,"width":256,"sizeGrid":"0,62,0,57","name":"GridLabel","height":137},"compId":71,"child":[{"type":"Script","props":{"runtime":"utils/rapidScroll/RapidItem.ts"},"compId":72}]},{"type":"Box","props":{"y":0,"x":0,"width":621,"sizeGrid":"0,62,0,57","name":"ItemLabel","mouseThrough":true,"height":137},"compId":73,"child":[{"type":"Script","props":{"runtime":"utils/rapidScroll/RapidItem.ts"},"compId":74},{"type":"Label","props":{"y":7,"x":14,"wordWrap":true,"width":24,"valign":"middle","text":"龙舰","strokeColor":"#bd654d","stroke":2,"name":"txtName","leading":13,"height":87,"fontSize":24,"color":"#fefaef","align":"center"},"compId":75,"child":[{"type":"Script","props":{"y":0,"x":0,"customType":"2","runtime":"utils/script/TTFComponent.ts"},"compId":76}]},{"type":"Label","props":{"y":22,"x":489,"width":132,"text":"龙舰","name":"txtTime","height":24,"fontSize":24,"color":"#0fa34e","align":"left"},"compId":84,"child":[{"type":"Script","props":{"y":0,"x":0,"customType":"2","runtime":"utils/script/TTFComponent.ts"},"compId":85}]}]}]},{"type":"Panel","props":{"y":149,"width":621,"var":"listPanel","itemChildPreList":"@arr:,","hitTestPrior":false,"height":714,"centerX":0,"anchorY":0,"anchorX":0},"compId":99},{"type":"HBox","props":{"y":110,"x":70,"var":"hbox","space":5},"compId":105,"child":[{"type":"Label","props":{"text":"今日运输次数：","fontSize":24,"color":"#6a5853"},"compId":53,"child":[{"type":"Script","props":{"y":0,"x":0,"customType":"2","runtime":"utils/script/TTFComponent.ts"},"compId":56}]},{"type":"Label","props":{"x":163,"var":"txtTransportCnt","text":"111","fontSize":24,"color":"#0fa34e"},"compId":54,"child":[{"type":"Script","props":{"customType":"2","runtime":"utils/script/TTFComponent.ts"},"compId":55}]}]}]}],"loadList":["res/image/com/common/bg_alert.png","res/image/com/common/img_titlezhuangshi.png","res/image/com/common/image_zhuangshi.png","res/image/com/common/frame_jinbidi.png","res/image/com/common/icon_zuanshi.png","res/image/com/common/btn_close2.png","res/image/com/common/image_itemBg.png","res/image/com/ship/zd_icon_shijian.png","res/image/com/ship/frame_ship1.png","res/image/com/ship/cy_jiaobiao_1.png","res/image/com/common/btn_yellow.png"],"loadList3D":[]}