{"type":"View","props":{"width":720,"height":1280},"compId":2,"child":[{"type":"Image","props":{"x":0,"var":"imgBg","skin":"res/image/com/jingji/bg_wangzhezhengba.jpg","centerY":0,"centerX":0},"compId":4,"child":[{"type":"Script","props":{"y":0,"x":0,"runtime":"utils/script/LoadResImage.ts"},"compId":43}]},{"type":"Box","props":{"top":0,"right":0,"left":0,"bottom":0},"compId":25,"child":[{"type":"Image","props":{"top":0,"skin":"res/image/com/jingji/frame_btdi.png","centerX":0},"compId":45,"child":[{"type":"Text","props":{"y":4,"x":218,"width":285,"var":"txtTitle","text":"王者争霸","height":32,"fontSize":32,"color":"#7b4826","align":"center","runtime":"Laya.Text"},"compId":46,"child":[{"type":"Script","props":{"customType":"1","runtime":"utils/script/TTFComponent.ts"},"compId":47}]}]},{"type":"Image","props":{"y":127,"x":230,"width":260,"var":"btn1","height":380},"compId":37},{"type":"Image","props":{"y":408,"x":22,"width":260,"var":"btn2","height":320},"compId":38},{"type":"Image","props":{"y":408,"x":434,"width":260,"var":"btn3","height":320},"compId":39},{"type":"Image","props":{"y":717,"x":42,"width":230,"var":"btn4","height":280},"compId":40},{"type":"Image","props":{"y":717,"x":439,"width":230,"var":"btn5","height":280},"compId":41},{"type":"Image","props":{"y":907,"x":262,"width":200,"var":"btn6","height":280},"compId":42},{"type":"Box","props":{"y":0,"x":0},"compId":48,"child":[{"type":"KingJJItem","props":{"y":100,"x":150,"var":"item1","scaleY":0.9,"scaleX":0.9,"runtime":"module/jingji/king/KingJJItem.ts"},"compId":49},{"type":"KingJJItem","props":{"y":450,"x":-4,"var":"item2","scaleY":0.7,"scaleX":0.7,"runtime":"module/jingji/king/KingJJItem.ts"},"compId":50},{"type":"KingJJItem","props":{"y":450,"x":400,"var":"item3","scaleY":0.7,"scaleX":0.7,"runtime":"module/jingji/king/KingJJItem.ts"},"compId":51},{"type":"KingJJItem","props":{"y":760,"x":12,"var":"item4","scaleY":0.65,"scaleX":0.65,"runtime":"module/jingji/king/KingJJItem.ts"},"compId":52},{"type":"KingJJItem","props":{"y":760,"x":401,"var":"item5","scaleY":0.65,"scaleX":0.65,"runtime":"module/jingji/king/KingJJItem.ts"},"compId":53},{"type":"KingJJItem","props":{"y":930,"x":211,"var":"item6","scaleY":0.65,"scaleX":0.65,"runtime":"module/jingji/king/KingJJItem.ts"},"compId":54}]},{"type":"Button","props":{"y":1187,"x":622,"var":"btnClose","stateNum":1,"skin":"res/image/com/common/btn_fanhui.png","right":23,"bottom":27},"compId":26,"child":[{"type":"Script","props":{"sound":"back","runtime":"utils/script/ScaleButton.ts"},"compId":27}]},{"type":"Button","props":{"y":67,"x":13,"var":"btnHlp","skin":"res/image/com/common/btn_wenhao.png","stateNum":1,"label":" "},"compId":33,"child":[{"type":"Script","props":{"y":0,"x":0,"runtime":"utils/script/ScaleButton.ts"},"compId":34}]}]}],"loadList":["res/image/com/jingji/bg_wangzhezhengba.jpg","res/image/com/jingji/frame_btdi.png","res/image/com/config/jingji/king/KingJJItem.scene","res/image/com/common/btn_fanhui.png","res/image/com/common/btn_wenhao.png"],"loadList3D":[]}